README.md
setup.cfg
setup.py
paysdegalles/__init__.py
paysdegalles/perceval_decorator.py
perceval_decorator.egg-info/PKG-INFO
perceval_decorator.egg-info/SOURCES.txt
perceval_decorator.egg-info/dependency_links.txt
perceval_decorator.egg-info/top_level.txt