Metadata-Version: 1.1
Name: perceval-decorator
Version: 0.0.1
Summary: Perceval\`s special technique.
Home-page: https://github.com/fanff/percevalDecorator
Author: fanf
Author-email: fanf@googlegroups.com
License: MIT
Keywords: perceval
Platform: UNKNOWN
Classifier: Development Status :: 5 - Production/Stable
Classifier: Intended Audience :: Developers
Classifier: License :: OSI Approved :: MIT License
Classifier: Programming Language :: Python :: 3
Classifier: Programming Language :: Python :: 3.2
Classifier: Programming Language :: Python :: 3.3
Classifier: Programming Language :: Python :: 3.4
